pi_device_net/__init__.py
pi_device_net/constants.py
pi_device_net/controller.py
pi_device_net/controller_manager.py
pi_device_net/interfaces.py
pi_device_net/module.py
pi_device_net/module_manager.py
pi_device_net/archivers/__init__.py
pi_device_net/archivers/archive_file.py
pi_device_net/archivers/archive_memory.py
pi_device_net/tests/__init__.py
pi_device_net/tests/manual_test_discovery.py
pi_device_net/tests/test_connect.py
pi_device_net/utility/__init__.py
pi_device_net/utility/statistics_fading.py
pi_device_net-0.1.30.dist-info/LICENSE
pi_device_net-0.1.30.dist-info/METADATA
pi_device_net-0.1.30.dist-info/WHEEL
pi_device_net-0.1.30.dist-info/top_level.txt
pi_device_net-0.1.30.dist-info/RECORD
