Metadata-Version: 2.1
Name: pi-device-net
Version: 0.1.30
Summary: A set of tools to operate a device network.
Home-page: https://github.com/EdwinWiseOne/PiDeviceNet
Author: Edwin Wise
Author-email: edwin@simreal.com
License: UNKNOWN
Platform: UNKNOWN
Classifier: Development Status :: 3 - Alpha
Classifier: Intended Audience :: Developers
Classifier: License :: Free for non-commercial use
Classifier: Programming Language :: Python :: 3 :: Only
Classifier: Topic :: Home Automation
Classifier: Topic :: Software Development :: Libraries
Requires-Python: >=3.7
Requires-Dist: paho-mqtt
Requires-Dist: pygame
